Metadata-Version: 1.0
Name: fin-functions
Version: 0.0.1
Summary: fin-functions
Home-page: https://github.com/njfix6/fin-functions
Author: Nicholas Fix
Author-email: njfix6@gmail.com
License: UNKNOWN
Platform: UNKNOWN
